game_puzzle_Bulls_and_Cows/__init__.py
game_puzzle_Bulls_and_Cows/validator.py
game_puzzle_bulls_and_cows-0.1.1.dist-info/licenses/LICENSE
game_puzzle_bulls_and_cows-0.1.1.dist-info/METADATA
game_puzzle_bulls_and_cows-0.1.1.dist-info/WHEEL
game_puzzle_bulls_and_cows-0.1.1.dist-info/top_level.txt
game_puzzle_bulls_and_cows-0.1.1.dist-info/RECORD
