Metadata-Version: 2.4
Name: game_puzzle_Bulls_and_Cows
Version: 0.1.1
Summary: game: puzzle: Bulls_and_Cows
Author: IK-dev
Author-email: my.secret.email@example.com
Classifier: Programming Language :: Python :: 3
Classifier: Operating System :: OS Independent
Requires-Python: >=3.6
License-File: LICENSE
Dynamic: author
Dynamic: author-email
Dynamic: classifier
Dynamic: license-file
Dynamic: requires-python
Dynamic: summary
